LICENSE
MANIFEST.in
README.md
requirements.txt
setup.cfg
setup.py
dagflow/__init__.py
dagflow/config.py
dagflow/dag.py
dagflow/event.py
dagflow/exceptions.py
dagflow/flow_operation.py
dagflow/loader.py
dagflow/manage.py
dagflow/plugin_registry.py
dagflow/sdk.py
dagflow/step.py
dagflow.egg-info/PKG-INFO
dagflow.egg-info/SOURCES.txt
dagflow.egg-info/dependency_links.txt
dagflow.egg-info/entry_points.txt
dagflow.egg-info/requires.txt
dagflow.egg-info/top_level.txt
dagflow.egg-info/zip-safe
dagflow/configs/__init__.py
dagflow/configs/logging_config.py
dagflow/dag_repos/__init__.py
dagflow/dag_repos/base_dag_repo.py
dagflow/dag_repos/mongodb_dag_repo.py
dagflow/event_center/__init__.py
dagflow/event_center/base_request_filter.py
dagflow/event_center/event_center.py
dagflow/executors/__init__.py
dagflow/executors/base_executor.py
dagflow/executors/celery_executor.py
dagflow/executors/sequential_executor.py
dagflow/message_queue/__init__.py
dagflow/message_queue/mq_broker.py
dagflow/plugins/__init__.py
dagflow/plugins/plugin_demo.py
dagflow/plugins/resource_filter.py
dagflow/tools/__init__.py
dagflow/tools/init_project.py
dagflow/tools/empty_project/__init__.py
dagflow/tools/empty_project/configs/__init__.py
dagflow/tools/empty_project/configs/dagflow_config.py
dagflow/tools/empty_project/dag_definitions/__init__.py
dagflow/tools/empty_project/plugins/__init__.py
dagflow/tools/empty_project/plugins/echo.py
dagflow/utils/__init__.py
dagflow/utils/cache_manager.py
dagflow/utils/class_loader.py
dagflow/utils/command.py
dagflow/utils/daemon.py
dagflow/utils/dlock.py
dagflow/utils/event_manager.py
dagflow/utils/message_queue.py
dagflow/utils/mongodb_operator.py
dagflow/utils/redis_operator.py
dagflow/utils/session_manager.py
testapp/__init__.py