Metadata-Version: 1.1
Name: dagflow
Version: 0.0.9
Summary: DAG Task Schedule Service
Home-page: https://github.com/godq/dagflow
Author: GodQ
Author-email: quchuanhao@gmail.com
License: Apache License, Version 2.0
Keywords: dag,flow,mq,task,schedule,dagflow
Platform: UNKNOWN
Classifier: Environment :: Console
Classifier: Programming Language :: Python :: 3.5
Classifier: Programming Language :: Python :: 3.6
Classifier: Programming Language :: Python :: 3.7
Classifier: Environment :: Web Environment
Classifier: Intended Audience :: Developers
Classifier: License :: OSI Approved :: Apache Software License
Classifier: Topic :: Utilities
Classifier: Topic :: System :: Monitoring
